requests_cloudkit/__init__.py
requests_cloudkit/cloudkit.py
requests_cloudkit/metadata.py
requests_cloudkit-1.0.1.dist-info/DESCRIPTION.rst
requests_cloudkit-1.0.1.dist-info/METADATA
requests_cloudkit-1.0.1.dist-info/RECORD
requests_cloudkit-1.0.1.dist-info/WHEEL
requests_cloudkit-1.0.1.dist-info/metadata.json
requests_cloudkit-1.0.1.dist-info/top_level.txt
