Metadata-Version: 2.0
Name: requests-cloudkit
Version: 1.0.1
Summary: Apple CloudKit server-to-server support for the requests Python library.
Home-page: https://github.com/lionheart/requests-cloudkit
Author: Dan Loewenherz
Author-email: dan@lionheartsw.com
License: Apache 2.0
Keywords: requests cloudkit
Platform: UNKNOWN
Classifier: Development Status :: 5 - Production/Stable
Classifier: Environment :: Console
Classifier: Intended Audience :: Developers
Classifier: License :: OSI Approved :: Apache Software License
Classifier: Natural Language :: English
Classifier: Operating System :: OS Independent
Classifier: Programming Language :: Python :: 2.6
Classifier: Programming Language :: Python :: 2.7
Classifier: Programming Language :: Python
Classifier: Topic :: Internet :: WWW/HTTP :: Dynamic Content :: CGI Tools/Libraries
Classifier: Topic :: Software Development :: Libraries :: Python Modules
Classifier: Topic :: Utilities
Provides-Extra: restmapper
Requires-Dist: requests (>=2.0.0)
Requires-Dist: ecdsa (>=0.13)
Provides-Extra: restmapper
Requires-Dist: requests (>=2.0.0); extra == 'restmapper'
Requires-Dist: ecdsa (>=0.13); extra == 'restmapper'
Requires-Dist: restmapper (>=0.1.0); extra == 'restmapper'
